slothtest/__init__.py
slothtest/sloth_config.py
slothtest/sloth_connector.py
slothtest/sloth_log.py
slothtest/sloth_watcher.py
slothtest/sloth_xml_converter.py
slothtest_pkg/__init__.py
slothtest_pkg/sloth_config.py
slothtest_pkg/sloth_connector.py
slothtest_pkg/sloth_log.py
slothtest_pkg/sloth_watcher.py
slothtest_pkg/sloth_xml_converter.py
slothtest-0.0.4.dist-info/LICENSE
slothtest-0.0.4.dist-info/METADATA
slothtest-0.0.4.dist-info/WHEEL
slothtest-0.0.4.dist-info/top_level.txt
slothtest-0.0.4.dist-info/RECORD
