Metadata-Version: 2.1
Name: slothtest
Version: 0.0.4
Summary: Sloth Test: An Automatic Unit Test Generator
Home-page: https://github.com/elegantwist/slothtest
Author: Paul Kovtun
Author-email: trademet@gmail.com
License: UNKNOWN
Platform: UNKNOWN
Classifier: Programming Language :: Python :: 3
Classifier: License :: OSI Approved :: MIT License
Classifier: Operating System :: OS Independent
Requires-Dist: joblib
